wizardhat/__init__.py
wizardhat/__version__.py
wizardhat/acquire.py
wizardhat/utils.py
wizardhat/buffers/__init__.py
wizardhat/buffers/buffers.py
wizardhat/plot/__init__.py
wizardhat/plot/plot.py
wizardhat/transform/__init__.py
wizardhat/transform/defaults.py
wizardhat/transform/transform.py
WizardHat-0.2.1.dist-info/LICENSE
WizardHat-0.2.1.dist-info/METADATA
WizardHat-0.2.1.dist-info/WHEEL
WizardHat-0.2.1.dist-info/top_level.txt
WizardHat-0.2.1.dist-info/RECORD
