Metadata-Version: 2.1
Name: WizardHat
Version: 0.2.1
Summary: Real-time processing and plotting of data streamed over LSL, with a focus on student-led BCI projects.
Home-page: https://github.com/merlin-neurotech/WizardHat
Author: Merlin Neurotech
Author-email: mnc@clubs.queensu.ca
License: BSD 3-Clause License
Platform: UNKNOWN
Classifier: License :: OSI Approved :: BSD License
Classifier: Programming Language :: Python
Classifier: Programming Language :: Python :: 3
Classifier: Programming Language :: Python :: 3.6
Classifier: Programming Language :: Python :: Implementation :: CPython
Classifier: Topic :: Scientific/Engineering
Classifier: Topic :: Scientific/Engineering :: Human Machine Interfaces
Classifier: Topic :: Scientific/Engineering :: Information Analysis
Classifier: Topic :: Scientific/Engineering :: Visualization
Classifier: Intended Audience :: Education
Classifier: Intended Audience :: Science/Research
Requires-Python: >=3.6.0
Requires-Dist: ble2lsl (==0.1.3)
Requires-Dist: matplotlib (>=2.2.0)
Requires-Dist: mne (>=0.15.2)
Requires-Dist: numpy (>=1.13.0)
Requires-Dist: pylsl (>=1.10.5)
Requires-Dist: scipy (>=1.0.0)
Requires-Dist: bokeh (>=0.13.0)
